vidsrc_search/__main__.py
vidsrc_search/argparsing.py
vidsrc_search/modules.py
vidsrc_search/term.py
vidsrc_search/utils.py
vidsrc_search/core/help.py
vidsrc_search/core/library.py
vidsrc_search/core/search.py
vidsrc_search/core/version.py
vidsrc_search-0.2.7.dist-info/LICENSE
vidsrc_search-0.2.7.dist-info/METADATA
vidsrc_search-0.2.7.dist-info/WHEEL
vidsrc_search-0.2.7.dist-info/entry_points.txt
vidsrc_search-0.2.7.dist-info/top_level.txt
vidsrc_search-0.2.7.dist-info/RECORD
