Metadata-Version: 2.1
Name: vidsrc-search
Version: 0.2.7
Summary: A pirate movie watcher written in Python
Project-URL: Homepage, https://github.com/SomedudeX/vidsrc-search
Project-URL: License, https://github.com/SomedudeX/vidsrc-search/blob/main/LICENSE
Project-URL: Changelog, https://github.com/SomedudeX/vidsrc-search/releases
Keywords: movie,video,search
Classifier: Development Status :: 4 - Beta
Classifier: Intended Audience :: End Users/Desktop
Classifier: License :: OSI Approved :: MIT License
Classifier: Programming Language :: Python :: 3 :: Only
Classifier: Programming Language :: Python
Classifier: Topic :: Multimedia
Classifier: Topic :: Utilities
Classifier: Environment :: Console
Requires-Python: >=3.8
License-File: LICENSE
Requires-Dist: aiohttp >=3.9.3
Requires-Dist: thefuzz >=0.22.1
Requires-Dist: tabulate >=0.9.0
Requires-Dist: requests >=2.31.0
Requires-Dist: tqdm >=4.66.2
